Metadata-Version: 2.1
Name: investingpy
Version: 0.0.1
Summary: Financial Data Extraction from Investing.com with Python
Home-page: https://investpy.readthedocs.io/
Author: Alvaro Bartolome
Author-email: alvarobdc@yahoo.com
License: MIT License
Download-URL: https://github.com/alvarobartt/investpy/archive/1.0.7.tar.gz
Project-URL: Bug Reports, https://github.com/alvarobartt/investpy/issues
Project-URL: Source, https://github.com/alvarobartt/investpy
Project-URL: Documentation, https://investpy.readthedocs.io/
Keywords: investing,investing-api,historical-data,financial-data,stocks,funds,etfs,indices,currency crosses,bonds,commodities,crypto currencies
Platform: UNKNOWN
Classifier: Development Status :: 4 - Beta
Classifier: Programming Language :: Python :: 3 :: Only
Classifier: Programming Language :: Python :: 3.6
Classifier: Programming Language :: Python :: 3.7
Classifier: Programming Language :: Python :: 3.8
Classifier: Programming Language :: Python :: 3.9
Classifier: License :: OSI Approved :: MIT License
Classifier: Intended Audience :: Developers
Classifier: Topic :: Office/Business :: Financial
Classifier: Topic :: Office/Business :: Financial :: Investment
Classifier: Topic :: Scientific/Engineering :: Information Analysis
Classifier: Topic :: Software Development :: Libraries
Requires-Python: >=3
License-File: LICENSE
Requires-Dist: Unidecode (>=1.1.1)
Requires-Dist: setuptools (>=41.2.0)
Requires-Dist: numpy (>=1.17.2)
Requires-Dist: pandas (>=0.25.1)
Requires-Dist: lxml (>=4.4.1)
Requires-Dist: requests (>=2.22.0)
Requires-Dist: pytz (>=2019.3)
Provides-Extra: docs
Requires-Dist: sphinx (==3.4.3) ; extra == 'docs'
Requires-Dist: recommonmark (==0.7.1) ; extra == 'docs'
Requires-Dist: furo (==2021.4.11b34) ; extra == 'docs'
Requires-Dist: investpy (==1.0.7) ; extra == 'docs'
Provides-Extra: tests
Requires-Dist: pytest (==6.1.1) ; extra == 'tests'
Requires-Dist: codecov (==2.1.10) ; extra == 'tests'
Requires-Dist: pytest-cov (==2.10.1) ; extra == 'tests'
